pilatte/__init__.py
pilatte/entrypoint.py
pilatte-0.0.1.dist-info/LICENSE
pilatte-0.0.1.dist-info/METADATA
pilatte-0.0.1.dist-info/WHEEL
pilatte-0.0.1.dist-info/top_level.txt
pilatte-0.0.1.dist-info/RECORD
