Metadata-Version: 2.1
Name: pilatte
Version: 0.0.1
Summary: The pilatte package
Home-page: https://github.com/pypa/sampleproject
Author: Pilatte
Author-email: pypi.org.wdubdvyyw6.20220202.125410@pilatte.be
License: UNKNOWN
Platform: UNKNOWN
Classifier: Programming Language :: Python :: 3
Classifier: License :: OSI Approved :: MIT License
Classifier: Operating System :: OS Independent
Requires-Python: >=3.10
License-File: LICENSE
